helloworldc066891/__init__.py
helloworldc066891/helloworldc066891.py
helloworldc066891-1.0.dist-info/METADATA
helloworldc066891-1.0.dist-info/WHEEL
helloworldc066891-1.0.dist-info/top_level.txt
helloworldc066891-1.0.dist-info/RECORD
