Metadata-Version: 2.1
Name: helloworldc066891
Version: 1.0
Summary: A simple Python library that prints "Hello, World!"
Author: Your Name
